mel_cepstral_distance/__init__.py
mel_cepstral_distance/alignment.py
mel_cepstral_distance/api.py
mel_cepstral_distance/computation.py
mel_cepstral_distance/helper.py
mel_cepstral_distance/py.typed
mel_cepstral_distance/silence.py
mel_cepstral_distance-0.0.4.dist-info/licenses/LICENSE
mel_cepstral_distance-0.0.4.dist-info/METADATA
mel_cepstral_distance-0.0.4.dist-info/WHEEL
mel_cepstral_distance-0.0.4.dist-info/top_level.txt
mel_cepstral_distance-0.0.4.dist-info/RECORD
