Metadata-Version: 2.4
Name: mel-cepstral-distance
Version: 0.0.4
Summary: A Python library for computing the Mel-Cepstral Distance (also known as Mel-Cepstral Distortion, MCD) between two inputs. This implementation is based on the paper 'Mel-Cepstral Distance Measure for Objective Speech Quality Assessment' by Kubichek (1993).
Author: Stefan Taubert, Jasmin Sternkopf
Maintainer: Stefan Taubert
License: MIT License
Project-URL: Homepage, https://github.com/jasminsternkopf/mel_cepstral_distance
Project-URL: Issues, https://github.com/jasminsternkopf/mel_cepstral_distance/issues
Keywords: TTS,Text-to-speech,Speech synthesis,MCD,Mel,DTW,MFCC,Dynamic Time Warping,Cepstral,Spectrogram,Spectrum,Distance,Divergence,Distortion,Language,Linguistics
Classifier: Development Status :: 4 - Beta
Classifier: Operating System :: OS Independent
Classifier: Operating System :: MacOS
Classifier: Operating System :: POSIX
Classifier: Operating System :: POSIX :: BSD
Classifier: Operating System :: POSIX :: Linux
Classifier: Operating System :: Unix
Classifier: Operating System :: Microsoft :: Windows
Classifier: Programming Language :: Python
Classifier: Programming Language :: Python :: 3
Classifier: Programming Language :: Python :: 3.8
Classifier: Programming Language :: Python :: 3.9
Classifier: Programming Language :: Python :: 3.10
Classifier: Programming Language :: Python :: 3.11
Classifier: Programming Language :: Python :: 3.12
Classifier: Programming Language :: Python :: 3.13
Classifier: License :: OSI Approved :: MIT License
Classifier: Topic :: Multimedia :: Sound/Audio
Classifier: Topic :: Multimedia :: Sound/Audio :: Analysis
Classifier: Topic :: Multimedia :: Sound/Audio :: Sound Synthesis
Classifier: Topic :: Multimedia :: Sound/Audio :: Speech
Requires-Python: <3.14,>=3.8
License-File: LICENSE
Requires-Dist: numpy>=1.22.4
Requires-Dist: scipy>=1.8.0
Requires-Dist: fastdtw>=0.3.4
Provides-Extra: dev
Requires-Dist: pytest; extra == "dev"
Requires-Dist: pytest-cov; extra == "dev"
Requires-Dist: pytest-xdist; extra == "dev"
Requires-Dist: tox; extra == "dev"
Requires-Dist: ruff; extra == "dev"
Requires-Dist: mypy; extra == "dev"
Requires-Dist: rope; extra == "dev"
Requires-Dist: build; extra == "dev"
Requires-Dist: twine; extra == "dev"
Dynamic: license-file
